README
setup.py
ca_certs_locater/__init__.py
ca_certs_locater.egg-info/PKG-INFO
ca_certs_locater.egg-info/SOURCES.txt
ca_certs_locater.egg-info/dependency_links.txt
ca_certs_locater.egg-info/top_level.txt