Metadata-Version: 1.0
Name: ca-certs-locater
Version: 1.0
Summary: a ca-certs file locater for httplib2
Home-page: https://github.com/aleiphoenix/ca-certs-locater
Author: AR
Author-email: aleiphoenix@gmail.com
License: MIT
Platform: UNKNOWN
